cashfree_pg/__init__.py
cashfree_pg/api_client.py
cashfree_pg/api_response.py
cashfree_pg/configuration.py
cashfree_pg/exceptions.py
cashfree_pg/py.typed
cashfree_pg/rest.py
cashfree_pg/models/__init__.py
cashfree_pg/models/address_details.py
cashfree_pg/models/adjust_vendor_balance_request.py
cashfree_pg/models/adjust_vendor_balance_response.py
cashfree_pg/models/api_error.py
cashfree_pg/models/api_error404.py
cashfree_pg/models/api_error409.py
cashfree_pg/models/api_error502.py
cashfree_pg/models/app.py
cashfree_pg/models/app_payment_method.py
cashfree_pg/models/authentication_error.py
cashfree_pg/models/authorization_details.py
cashfree_pg/models/authorization_in_payments_entity.py
cashfree_pg/models/authorize_order_request.py
cashfree_pg/models/bad_request_error.py
cashfree_pg/models/balance_details.py
cashfree_pg/models/bank_details.py
cashfree_pg/models/banktransfer.py
cashfree_pg/models/banktransfer_payment_method.py
cashfree_pg/models/card.py
cashfree_pg/models/card_emi.py
cashfree_pg/models/card_emi_payment_method.py
cashfree_pg/models/card_offer.py
cashfree_pg/models/card_payment_method.py
cashfree_pg/models/cardless_emi.py
cashfree_pg/models/cardless_emi_entity.py
cashfree_pg/models/cardless_emi_payment_method.py
cashfree_pg/models/cardless_emi_queries.py
cashfree_pg/models/cart_details.py
cashfree_pg/models/cart_details_entity.py
cashfree_pg/models/cart_item.py
cashfree_pg/models/cashback_details.py
cashfree_pg/models/charges_details.py
cashfree_pg/models/charges_entity.py
cashfree_pg/models/create_customer_request.py
cashfree_pg/models/create_link_request.py
cashfree_pg/models/create_offer_request.py
cashfree_pg/models/create_order_request.py
cashfree_pg/models/create_order_settlement_request_body.py
cashfree_pg/models/create_order_settlement_request_body_meta_data.py
cashfree_pg/models/create_partner_vpa_request.py
cashfree_pg/models/create_plan_request.py
cashfree_pg/models/create_subscription_payment_request.py
cashfree_pg-5.0.5.dist-info/licenses/LICENSE.md
cashfree_pg-5.0.5.dist-info/METADATA
cashfree_pg-5.0.5.dist-info/WHEEL
cashfree_pg-5.0.5.dist-info/top_level.txt
cashfree_pg-5.0.5.dist-info/RECORD
