Metadata-Version: 2.4
Name: cashfree_pg
Version: 5.0.5
Summary: Cashfree Payment Gateway APIs
Home-page: https://cashfree.com
Author: Cashfree Payments
Author-email: developers@cashfree.com
License: Apache 2.0
Keywords: Payment Gateway,Cashfree,SDK,Payments,Cashfree Payment Gateway APIs
License-File: LICENSE.md
Requires-Dist: urllib3<2.1.0,>=1.25.3
Requires-Dist: python-dateutil
Requires-Dist: sentry-sdk<1.33.0,>=1.32.0
Requires-Dist: pydantic>=2.11.7
Requires-Dist: aenum
Dynamic: author
Dynamic: author-email
Dynamic: description
Dynamic: description-content-type
Dynamic: home-page
Dynamic: keywords
Dynamic: license
Dynamic: license-file
Dynamic: requires-dist
Dynamic: summary
